pydantic_forms/__init__.py
pydantic_forms/exceptions.py
pydantic_forms/py.typed
pydantic_forms/types.py
pydantic_forms/core/__init__.py
pydantic_forms/core/asynchronous.py
pydantic_forms/core/shared.py
pydantic_forms/core/sync.py
pydantic_forms/core/translations.py
pydantic_forms/exception_handlers/__init__.py
pydantic_forms/exception_handlers/fastapi.py
pydantic_forms/utils/__init__.py
pydantic_forms/utils/json.py
pydantic_forms/utils/schema.py
pydantic_forms/validators/__init__.py
pydantic_forms/validators/helpers.py
pydantic_forms/validators/components/__init__.py
pydantic_forms/validators/components/accept.py
pydantic_forms/validators/components/choice.py
pydantic_forms/validators/components/choice_list.py
pydantic_forms/validators/components/contact_person.py
pydantic_forms/validators/components/contact_person_list.py
pydantic_forms/validators/components/display_subscription.py
pydantic_forms/validators/components/divider.py
pydantic_forms/validators/components/hidden.py
pydantic_forms/validators/components/label.py
pydantic_forms/validators/components/list_of_one.py
pydantic_forms/validators/components/list_of_two.py
pydantic_forms/validators/components/long_text.py
pydantic_forms/validators/components/migration_summary.py
pydantic_forms/validators/components/organisation_id.py
pydantic_forms/validators/components/read_only.py
pydantic_forms/validators/components/timestamp.py
pydantic_forms/validators/components/unique_constrained_list.py
pydantic_forms-2.1.2.dist-info/licenses/LICENSE
pydantic_forms-2.1.2.dist-info/WHEEL
pydantic_forms-2.1.2.dist-info/METADATA
pydantic_forms-2.1.2.dist-info/RECORD
