Metadata-Version: 2.4
Name: pydantic-forms
Version: 2.1.2
Summary: Pydantic-forms engine.
Home-page: https://github.com/workfloworchestrator/pydantic-forms
Author: SURF
Author-email: automation-beheer@surf.nl
Requires-Python: >=3.9,<=3.14
Classifier: Intended Audience :: Information Technology
Classifier: Intended Audience :: System Administrators
Classifier: Operating System :: OS Independent
Classifier: Programming Language :: Python :: 3
Classifier: Programming Language :: Python
Classifier: Topic :: Internet
Classifier: Topic :: Software Development :: Libraries :: Application Frameworks
Classifier: Topic :: Software Development :: Libraries :: Python Modules
Classifier: Topic :: Software Development :: Libraries
Classifier: Topic :: Software Development
Classifier: Typing :: Typed
Classifier: Development Status :: 4 - Beta
Classifier: Environment :: Web Environment
Classifier: Framework :: AsyncIO
Classifier: Framework :: FastAPI
Classifier: Framework :: Flask
Classifier: Framework :: Pydantic :: 2
Classifier: Intended Audience :: Developers
Classifier: Intended Audience :: Telecommunications Industry
Classifier: License :: OSI Approved :: Apache Software License
Classifier: Programming Language :: Python :: 3 :: Only
Classifier: Programming Language :: Python :: 3.9
Classifier: Programming Language :: Python :: 3.10
Classifier: Programming Language :: Python :: 3.11
Classifier: Programming Language :: Python :: 3.12
Classifier: Programming Language :: Python :: 3.13
Classifier: Topic :: Internet :: WWW/HTTP :: HTTP Servers
Classifier: Topic :: Internet :: WWW/HTTP
License-File: LICENSE
Requires-Dist: more-itertools
Requires-Dist: pydantic[email]>=2.7.4
Requires-Dist: pydantic-i18n==0.4.5
Requires-Dist: toml ; extra == "dev"
Requires-Dist: bumpversion ; extra == "dev"
Requires-Dist: mypy_extensions ; extra == "dev"
Requires-Dist: pre-commit ; extra == "dev"
Requires-Dist: pydocstyle ; extra == "dev"
Requires-Dist: python-dotenv ; extra == "dev"
Requires-Dist: watchdog ; extra == "dev"
Requires-Dist: mkdocs ; extra == "doc"
Requires-Dist: mkdocs-material ; extra == "doc"
Requires-Dist: mkdocs-render-swagger-plugin ; extra == "doc"
Requires-Dist: mkdocs-include-markdown-plugin ; extra == "doc"
Requires-Dist: fastapi >=0.80.0 ; extra == "fastapi"
Requires-Dist: orjson >=3.6.0,<4.0.0 ; extra == "orjson"
Requires-Dist: apache-license-check ; extra == "test"
Requires-Dist: black ; extra == "test"
Requires-Dist: structlog ; extra == "test"
Requires-Dist: jsonref ; extra == "test"
Requires-Dist: mypy==1.6.1 ; extra == "test"
Requires-Dist: pytest ; extra == "test"
Requires-Dist: pytest-cov ; extra == "test"
Requires-Dist: pytest-asyncio ; extra == "test"
Requires-Dist: pytest-xdist ; extra == "test"
Requires-Dist: ruff ; extra == "test"
Requires-Dist: types-Deprecated ; extra == "test"
Requires-Dist: types-certifi ; extra == "test"
Requires-Dist: types-python-dateutil ; extra == "test"
Requires-Dist: types-pytz ; extra == "test"
Requires-Dist: types-toml ; extra == "test"
Requires-Dist: types-ujson ; extra == "test"
Requires-Dist: types-orjson ; extra == "test"
Project-URL: Documentation, https://github.com/workfloworchestrator/pydantic-forms/blob/main/README.md
Provides-Extra: dev
Provides-Extra: doc
Provides-Extra: fastapi
Provides-Extra: orjson
Provides-Extra: test
